toxinpred3/merci/MERCI_motif_locator.pl
toxinpred3/model/toxinpred3.0_model.pkl
toxinpred3/motifs/neg_motif.txt
toxinpred3/motifs/pos_motif.txt
toxinpred3/python_scripts/__init__.py
toxinpred3/python_scripts/toxinpred3.py
toxinpred3-1.4.dist-info/LICENSE.txt
toxinpred3-1.4.dist-info/METADATA
toxinpred3-1.4.dist-info/WHEEL
toxinpred3-1.4.dist-info/entry_points.txt
toxinpred3-1.4.dist-info/top_level.txt
toxinpred3-1.4.dist-info/RECORD
