Metadata-Version: 2.1
Name: toxinpred3
Version: 1.4
Summary: A tool to predict toxic and non-toxic peptides
Home-page: https://github.com/raghavagps/toxinpred3
Requires-Python: >=3.6
License-File: LICENSE.txt
Requires-Dist: numpy
Requires-Dist: pandas
Requires-Dist: argparse
Requires-Dist: joblib
